CHANGELOG.md
LICENSE.txt
MANIFEST.in
README.md
cielcg.py
setup.py
cielcg.egg-info/PKG-INFO
cielcg.egg-info/SOURCES.txt
cielcg.egg-info/dependency_links.txt
cielcg.egg-info/not-zip-safe
cielcg.egg-info/top_level.txt